HotnCold/HotnCold.py
HotnCold/__init__.py
HotnCold-1.2.0.dist-info/LICENSE
HotnCold-1.2.0.dist-info/METADATA
HotnCold-1.2.0.dist-info/WHEEL
HotnCold-1.2.0.dist-info/entry_points.txt
HotnCold-1.2.0.dist-info/top_level.txt
HotnCold-1.2.0.dist-info/RECORD
