Metadata-Version: 2.1
Name: HotnCold
Version: 1.2.0
Summary: a Hot and Cold Game
Home-page: https://gitlab.com/samic130/hotncold/
Author: Samic
Author-email: hotncold@samic.org
License: GPLv3
Project-URL: Bug Tracker, https://gitlab.com/samic130/hotncold/-/issues
Platform: UNKNOWN
Classifier: Programming Language :: Python :: 3
Classifier: License :: OSI Approved :: GNU General Public License v3 (GPLv3)
Classifier: Operating System :: OS Independent
Requires-Python: >=3.0
License-File: LICENSE
Requires-Dist: matplotlib
